mcpandroidbuild/__init__.py
mcpandroidbuild/__main__.py
mcpandroidbuild/build.sh
mcpandroidbuild/instrumentedTest.sh
mcpandroidbuild/server.py
mcpandroidbuild/test.sh
mcpandroidbuild-0.10.0.dist-info/METADATA
mcpandroidbuild-0.10.0.dist-info/WHEEL
mcpandroidbuild-0.10.0.dist-info/entry_points.txt
mcpandroidbuild-0.10.0.dist-info/licenses/LICENSE
mcpandroidbuild-0.10.0.dist-info/RECORD
