Metadata-Version: 2.4
Name: mcpandroidbuild
Version: 0.10.0
Summary: A MCP tool that builds Android project and send error back. It also helps to run test and feed the error back to llm.
Author: Tim Wang
Maintainer-email: Tim Wang <overocean@gmail.com>
License: MIT
License-File: LICENSE
Keywords: Android,automation,http,llm,mcp
Classifier: Development Status :: 4 - Beta
Classifier: Intended Audience :: Developers
Classifier: License :: OSI Approved :: MIT License
Classifier: Programming Language :: Python :: 3
Classifier: Programming Language :: Python :: 3.10
Requires-Python: >=3.13
Requires-Dist: httpx>=0.28.1
Requires-Dist: mcp[cli]>=1.3.0
